polyscope_bindings.cpython-313-aarch64-linux-gnu.so
include/polyscope/affine_remapper.h
include/polyscope/affine_remapper.ipp
include/polyscope/camera_parameters.h
include/polyscope/camera_parameters.ipp
include/polyscope/camera_view.h
include/polyscope/camera_view.ipp
include/polyscope/check_invalid_values.h
include/polyscope/color_image_quantity.h
include/polyscope/color_management.h
include/polyscope/color_quantity.h
include/polyscope/color_quantity.ipp
include/polyscope/color_render_image_quantity.h
include/polyscope/colors.h
include/polyscope/combining_hash_functions.h
include/polyscope/context.h
include/polyscope/curve_network.h
include/polyscope/curve_network.ipp
include/polyscope/curve_network_color_quantity.h
include/polyscope/curve_network_quantity.h
include/polyscope/curve_network_scalar_quantity.h
include/polyscope/curve_network_vector_quantity.h
include/polyscope/depth_render_image_quantity.h
include/polyscope/disjoint_sets.h
include/polyscope/elementary_geometry.h
include/polyscope/file_helpers.h
include/polyscope/floating_quantities.h
include/polyscope/floating_quantity.h
include/polyscope/floating_quantity_structure.h
include/polyscope/floating_quantity_structure.ipp
include/polyscope/fullscreen_artist.h
include/polyscope/group.h
include/polyscope/histogram.h
include/polyscope/image_quantity.h
include/polyscope/image_quantity_base.h
include/polyscope/imgui_config.h
include/polyscope/implicit_helpers.h
include/polyscope/implicit_helpers.ipp
include/polyscope/internal.h
include/polyscope/messages.h
include/polyscope/numeric_helpers.h
include/polyscope/options.h
include/polyscope/parameterization_quantity.h
include/polyscope/parameterization_quantity.ipp
include/polyscope/persistent_value.h
include/polyscope/pick.h
include/polyscope/pick.ipp
include/polyscope/point_cloud.h
include/polyscope/point_cloud.ipp
include/polyscope/point_cloud_color_quantity.h
polyscope-2.5.0.dist-info/METADATA
polyscope-2.5.0.dist-info/WHEEL
polyscope-2.5.0.dist-info/RECORD
polyscope-2.5.0.dist-info/licenses/LICENSE
