Metadata-Version: 2.1
Name: polyscope
Version: 2.5.0
Summary: Polyscope: A viewer and user interface for 3D data.
Author-Email: Nicholas Sharp <nmwsharp@gmail.com>
Maintainer-Email: Nicholas Sharp <nmwsharp@gmail.com>
License: MIT License
Classifier: Development Status :: 5 - Production/Stable
Classifier: License :: OSI Approved :: MIT License
Classifier: Programming Language :: Python :: 3
Project-URL: Homepage, https://github.com/nmwsharp/polyscope
Project-URL: Documentation, https://polyscope.run
Project-URL: Bug tracker, https://github.com/nmwsharp/polyscope/issues
Project-URL: Discussions, https://github.com/nmwsharp/polyscope/discussions
Requires-Python: >=3.7
Requires-Dist: numpy
